scipdf/__init__.py
scipdf/features/__init__.py
scipdf/features/text_utils.py
scipdf/pdf/__init__.py
scipdf/pdf/parse_pdf.py
scipdf/pdf/pdffigures2/pdffigures2-assembly-0.0.12-SNAPSHOT.jar
scipdf_mirror-0.1.dev0.data/scripts/serve_grobid.sh
scipdf_mirror-0.1.dev0.dist-info/METADATA
scipdf_mirror-0.1.dev0.dist-info/WHEEL
scipdf_mirror-0.1.dev0.dist-info/top_level.txt
scipdf_mirror-0.1.dev0.dist-info/RECORD
