Metadata-Version: 2.1
Name: scipdf-mirror
Version: 0.1.dev0
Summary: Python parser for scientific PDF based on GROBID.
Home-page: https://github.com/titipata/scipdf_parser
Author: Titipat Achakulvisut
Author-email: my.titipat@gmail.com
License: (c) MIT License 2019 Titipat Achakulvisut
Keywords: PDF parser,GROBID,Python PDF parser
Platform: UNKNOWN
Classifier: Programming Language :: Python :: 3
Classifier: License :: OSI Approved :: MIT License
Classifier: Operating System :: OS Independent
Requires-Dist: lxml
Requires-Dist: pandas
Requires-Dist: requests
Requires-Dist: spacy
Requires-Dist: textstat
